saveimg/__init__.py
saveimg/cli.py
saveimg/exceptions.py
saveimg/generate.py
saveimg/logger.py
mkdataset-0.1.dist-info/METADATA
mkdataset-0.1.dist-info/WHEEL
mkdataset-0.1.dist-info/entry_points.txt
mkdataset-0.1.dist-info/top_level.txt
mkdataset-0.1.dist-info/RECORD
